sarc/__init__.py
sarc/__main__.py
sarc/_version.py
sarc/aglenv_file_info.json
sarc/sarc.py
sarc-2.0.5.dist-info/LICENSE
sarc-2.0.5.dist-info/METADATA
sarc-2.0.5.dist-info/WHEEL
sarc-2.0.5.dist-info/entry_points.txt
sarc-2.0.5.dist-info/top_level.txt
sarc-2.0.5.dist-info/RECORD
