Metadata-Version: 2.1
Name: sarc
Version: 2.0.5
Summary: Nintendo SARC archive reader and writer
Home-page: https://github.com/leoetlino/sarc
Author: leoetlino
Author-email: leo@leolam.fr
Classifier: License :: OSI Approved :: GNU General Public License v2 or later (GPLv2+)
Classifier: Operating System :: OS Independent
Classifier: Programming Language :: Python :: 3 :: Only
Classifier: Topic :: Software Development :: Libraries
Requires-Python: >=3.6
License-File: LICENSE
Requires-Dist: rstb ~=1.0
Requires-Dist: oead ~=1.0
